{
  "key": "음식물류폐기물",
  "category": "음식물류폐기물",
  "이름": "음식물류폐기물",

  "대상_품목": [
    "식재료 및 식품의 생산·유통·조리 등의 과정에서 발생하는 쓰레기와 남겨서 버려지는 음식물"
  ],

  "대상_설명": [],

  "세부_품목": {
    "음식물류폐기물": [
      "곡식",
      "채소",
      "과일껍질",
      "상한음식",
      "남은 음식물"
    ]
  },

  "배출방법_공통": [],

  "배출방법_세부": {},

  "배출불가_품목_안내": {
    "동물의 뼈": "일반종량제폐기물로 배출",
    "소·돼지 등의 뼈": "일반종량제폐기물로 배출",
    "생선뼈": "일반종량제폐기물로 배출",
    "동물의 털·깃털": "일반종량제폐기물로 배출",
    "소·닭·등의 털·깃털": "일반종량제폐기물로 배출",
    "조개류의 껍데기": "일반종량제폐기물로 배출",
    "조개·전복 등의 껍데기": "일반종량제폐기물로 배출",
    "핵과류의 씨": "일반종량제폐기물로 배출",
    "복숭아·살구 등의 씨": "일반종량제폐기물로 배출",
    "알의 껍데기": "일반종량제폐기물로 배출",
    "닭·오리·메추리알 등의 껍데기": "일반종량제폐기물로 배출",
    "견과류의 껍데기": "일반종량제폐기물로 배출",
    "호두·코코넛·밤 등의 껍데기": "일반종량제폐기물로 배출",
    "곡류 및 콩류의 껍질": "일반종량제폐기물로 배출",
    "땅콩껍질·왕겨 등": "일반종량제폐기물로 배출",
    "맹독성 잔재물(복어내장 등)": "일반종량제폐기물로 배출",
    "복합재질 가공식품(티백·육수팩 등)": "일반종량제폐기물로 배출",
    "한약·차류의 찌꺼기": "일반종량제폐기물로 배출",
    "한약·커피·녹차 등의 찌꺼기": "일반종량제폐기물로 배출",
    "채소류의 뿌리·껍질": "일반종량제폐기물로 배출",
    "파·미나리 등 뿌리": "일반종량제폐기물로 배출",
    "양파·마늘·생강·옥수수 등 껍질": "일반종량제폐기물로 배출",
    "고추대·옥수수대": "일반종량제폐기물로 배출"
  },

  "아이콘_절차": []
}
